example_notebooks/__init__.py
example_notebooks/example.ipynb
example_notebooks/feature_subset_example.ipynb
example_notebooks/multimodel_example.ipynb
tests/__init__.py
tests/helpers.py
tests/test_account_cluster_transformer.py
tests/test_cluster_model.py
tests/test_custom_cluster_transformer.py
tests/test_feature_subset.py
tests/test_lw_cluster_model.py
tests/test_ml_helpers.py
tests/test_multi_model.py
tests/test_multi_transformer.py
tests/test_phasing_transformer.py
tests/test_prediction_model.py
tests/test_preprocessing.py
tests/test_terrain_model.py
tests/test_tool.py
vf_portalytics/__init__.py
vf_portalytics/cluster_model.py
vf_portalytics/dataset.py
vf_portalytics/feature_subset.py
vf_portalytics/lw_cluster_model.py
vf_portalytics/ml_helpers.py
vf_portalytics/model.py
vf_portalytics/multi_model.py
vf_portalytics/terrain_config.py
vf_portalytics/terrain_model.py
vf_portalytics/tool.py
vf_portalytics/viz.py
vf_portalytics-2.1.2.dist-info/LICENSE
vf_portalytics-2.1.2.dist-info/METADATA
vf_portalytics-2.1.2.dist-info/WHEEL
vf_portalytics-2.1.2.dist-info/pbr.json
vf_portalytics-2.1.2.dist-info/top_level.txt
vf_portalytics-2.1.2.dist-info/RECORD
