Metadata-Version: 2.1
Name: vf_portalytics
Version: 2.1.2
Summary: A consistent interface for creating Machine Learning Models compatible with VisualFabriq environment
Home-page: https://github.com/visualfabriq/portalytics
Author: Christos Tselas
Author-email: ctselas@visualfabriq.com
Maintainer: DataFlow Domain
Maintainer-email: cvaartjes@visualfabriq.com
Platform: any
Classifier: Development Status :: 4 - Beta
Classifier: Intended Audience :: Developers
Classifier: Intended Audience :: Information Technology
Classifier: Intended Audience :: Science/Research
Classifier: License :: OSI Approved :: BSD License
Classifier: Programming Language :: Python
Classifier: Topic :: Software Development :: Libraries :: Python Modules
Classifier: Operating System :: Microsoft :: Windows
Classifier: Operating System :: Unix
Classifier: Programming Language :: Python :: 3
Classifier: Programming Language :: Python :: 3.11
License-File: LICENSE
Requires-Dist: joblib ==1.4.2
Requires-Dist: numpy >=2
Requires-Dist: pandas ~=2.2.2
Requires-Dist: scikit-learn ==1.5.1
Requires-Dist: xgboost ==2.1.0
Requires-Dist: scipy ==1.14.0
Requires-Dist: category-encoders ==2.6.3
Requires-Dist: numexpr >=2.7.1
Requires-Dist: seaborn >=0.10.1
Requires-Dist: statsmodels >=0.12.0
Requires-Dist: hyperopt >=0.2.5
